{
  "export_date": "2025-09-30T12:50:58.364050",
  "summary": {
    "total_customers": 3,
    "total_revenue": 12744.369999999999,
    "total_transactions": 7,
    "analysis_period": {
      "start": "2024-02-23",
      "end": "2024-06-14"
    }
  },
  "customers": [
    {
      "customer_id": "Absa_DM",
      "total_transactions": 2,
      "total_spent": 10500.0,
      "average_transaction": 5250.0,
      "median_transaction": 5250.0,
      "min_transaction": 1500.0,
      "max_transaction": 9000.0,
      "std_deviation": 5303.300858899106,
      "first_transaction": "2024-02-23",
      "last_transaction": "2024-06-14",
      "active_days": 112,
      "transaction_frequency": 0.5357142857142857,
      "most_common_amount": 1500.0,
      "card_numbers_used": [],
      "spending_trend": "Increasing",
      "trend_strength": 1500.0000000000002
    },
    {
      "customer_id": "Card_2676",
      "total_transactions": 3,
      "total_spent": 2224.37,
      "average_transaction": 741.4566666666666,
      "median_transaction": 459.27,
      "min_transaction": 80.0,
      "max_transaction": 1685.1,
      "std_deviation": 838.9329464464566,
      "first_transaction": "2024-06-09",
      "last_transaction": "2024-06-13",
      "active_days": 4,
      "transaction_frequency": 22.5,
      "most_common_amount": 80.0,
      "card_numbers_used": [
        "2676"
      ],
      "spending_trend": "Insufficient Data",
      "trend_strength": 0.0
    },
    {
      "customer_id": "Kamel_Potteries",
      "total_transactions": 2,
      "total_spent": 20.0,
      "average_transaction": 10.0,
      "median_transaction": 10.0,
      "min_transaction": 10.0,
      "max_transaction": 10.0,
      "std_deviation": 0.0,
      "first_transaction": "2024-02-23",
      "last_transaction": "2024-02-26",
      "active_days": 3,
      "transaction_frequency": 20.0,
      "most_common_amount": 10.0,
      "card_numbers_used": [],
      "spending_trend": "Insufficient Data",
      "trend_strength": 0.0
    }
  ],
  "segments": [
    {
      "customer_id": "Absa_DM",
      "segment": "Regular",
      "segment_priority": 3,
      "frequency_category": "Rare",
      "transaction_size": "Very Large",
      "total_spent": 10500.0,
      "transaction_count": 2,
      "average_transaction": 5250.0,
      "spending_trend": "Increasing",
      "retention_risk": "Low"
    },
    {
      "customer_id": "Card_2676",
      "segment": "Low Value",
      "segment_priority": 5,
      "frequency_category": "Very Frequent",
      "transaction_size": "Small",
      "total_spent": 2224.37,
      "transaction_count": 3,
      "average_transaction": 741.4566666666666,
      "spending_trend": "Insufficient Data",
      "retention_risk": "High"
    },
    {
      "customer_id": "Kamel_Potteries",
      "segment": "Low Value",
      "segment_priority": 5,
      "frequency_category": "Very Frequent",
      "transaction_size": "Micro",
      "total_spent": 20.0,
      "transaction_count": 2,
      "average_transaction": 10.0,
      "spending_trend": "Insufficient Data",
      "retention_risk": "High"
    }
  ]
}